hackertype.py
hackertype-0.1.dist-info/LICENSE
hackertype-0.1.dist-info/METADATA
hackertype-0.1.dist-info/WHEEL
hackertype-0.1.dist-info/entry_points.txt
hackertype-0.1.dist-info/top_level.txt
hackertype-0.1.dist-info/RECORD
