Metadata-Version: 2.1
Name: hackertype
Version: 0.1
Summary: Type like a holywood movie hacker
Home-page: https://github.com/ddaletski/hackertype
Author: Denis Daletski
Author-email: daletskidenis@gmail.com
License: UNKNOWN
Platform: UNKNOWN
Classifier: Programming Language :: Python :: 3
Classifier: License :: OSI Approved :: MIT License
Classifier: Operating System :: OS Independent
Requires-Python: >=3.5
Requires-Dist: Click
